intersection_control/__init__.py
intersection_control/algorithms/__init__.py
intersection_control/algorithms/qb_im/__init__.py
intersection_control/algorithms/qb_im/_visualise.py
intersection_control/algorithms/qb_im/constants.py
intersection_control/algorithms/qb_im/qb_im_intersection_manager.py
intersection_control/algorithms/qb_im/qb_im_vehicle.py
intersection_control/algorithms/rl_im/__init__.py
intersection_control/algorithms/rl_im/constants.py
intersection_control/algorithms/rl_im/rl_vehicle.py
intersection_control/algorithms/rl_im/training/__init__.py
intersection_control/algorithms/rl_im/training/single_intersection_sumo_env.py
intersection_control/algorithms/rl_im/training/train.py
intersection_control/algorithms/stip/__init__.py
intersection_control/algorithms/stip/constants.py
intersection_control/algorithms/stip/stip_vehicle.py
intersection_control/algorithms/traffic_light/__init__.py
intersection_control/algorithms/traffic_light/tl_intersection_manager.py
intersection_control/algorithms/traffic_light/tl_vehicle.py
intersection_control/algorithms/utils/__init__.py
intersection_control/algorithms/utils/discretised_intersection.py
intersection_control/communication/__init__.py
intersection_control/communication/distance_based_unit.py
intersection_control/core/__init__.py
intersection_control/core/communication.py
intersection_control/core/performance_indication.py
intersection_control/core/algorithm/__init__.py
intersection_control/core/algorithm/intersection_manager.py
intersection_control/core/algorithm/vehicle.py
intersection_control/core/environment/__init__.py
intersection_control/core/environment/environment.py
intersection_control/core/environment/intersection_handler.py
intersection_control/core/environment/vehicle_handler.py
intersection_control/environments/__init__.py
intersection_control/environments/sumo/__init__.py
intersection_control/environments/sumo/sumo_environment.py
intersection_control/environments/sumo/sumo_intersection_handler.py
intersection_control-0.2.0.dist-info/LICENSE
intersection_control-0.2.0.dist-info/METADATA
intersection_control-0.2.0.dist-info/WHEEL
intersection_control-0.2.0.dist-info/top_level.txt
intersection_control-0.2.0.dist-info/RECORD
