Metadata-Version: 2.1
Name: intersection-control
Version: 0.2.0
Summary: An environment-agnostic framework for implementing and comparing intersection control algorithms
Home-page: https://github.com/julesdehon/IntersectionControl
Author: Jules Dehon
License: MIT
Requires-Python: >=3.7
License-File: LICENSE
Requires-Dist: numpy
Requires-Dist: ray (>=1.12)
Requires-Dist: gym
Requires-Dist: Shapely
Provides-Extra: deploy
Requires-Dist: myst-parser ; extra == 'deploy'
Requires-Dist: karma-sphinx-theme ; extra == 'deploy'
